LICENSE.txt
MANIFEST.in
README.md
README.rst
setup.py
bygone/__init__.py
bygone/__version__.py
bygone/cl_utils.py
bygone/default_settings.yaml
bygone/setup.cfg
bygone/utKit.py
bygone.egg-info/PKG-INFO
bygone.egg-info/SOURCES.txt
bygone.egg-info/dependency_links.txt
bygone.egg-info/not-zip-safe
bygone.egg-info/requires.txt
bygone.egg-info/top_level.txt
bygone/commonutils/__init__.py
bygone/commonutils/getpackagepath.py
bygone/tests/__init__.py