Metadata-Version: 1.1
Name: bygone
Version: 0.1
Summary: A python package and command-line tools to Life-logging
Home-page: https://github.com/thespacedoctor/bygone
Author: David Young
Author-email: davidrobertyoung@gmail.com
License: MIT
Download-URL: https://github.com/thespacedoctor/bygone/archive/v0.1.zip
Keywords: life-logging
Platform: UNKNOWN
Classifier: Development Status :: 4 - Beta
Classifier: License :: OSI Approved :: MIT License
Classifier: Programming Language :: Python :: 2.7
Classifier: Topic :: Utilities
